algo_ops/__init__.py
algo_ops/dependency/__init__.py
algo_ops/dependency/sys_util.py
algo_ops/dependency/tester_util.py
algo_ops/ops/__init__.py
algo_ops/ops/cv.py
algo_ops/ops/op.py
algo_ops/ops/settings.py
algo_ops/ops/text.py
algo_ops/paraloop/__init__.py
algo_ops/paraloop/paraloop.py
algo_ops/paraloop/test/test_paraloop.py
algo_ops/pickleable_object/__init__.py
algo_ops/pickleable_object/pickleable_object.py
algo_ops/pickleable_object/test/test_pickleable_object.py
algo_ops/pipeline/__init__.py
algo_ops/pipeline/cv_pipeline.py
algo_ops/pipeline/pipeline.py
algo_ops/plot/__init__.py
algo_ops/plot/plot.py
algo_ops/test/test_cv_pipeline.py
algo_ops/test/test_framework.py
algo_ops/test/data/joy_of_data.png
algo_ops-0.0.1.7.1.dist-info/METADATA
algo_ops-0.0.1.7.1.dist-info/WHEEL
algo_ops-0.0.1.7.1.dist-info/licenses/LICENSE
algo_ops-0.0.1.7.1.dist-info/RECORD
