Metadata-Version: 2.1
Name: algo-ops
Version: 0.0.1.7.1
Summary: Algo-Ops Framework
Project-URL: Homepage, https://github.com/prateekt/algo-ops
Project-URL: Bug Tracker, https://github.com/prateekt/algo-ops/issues
Author-email: Prateek Tandon <prateek1.tandon@gmail.com>
License-Expression: MIT
License-File: LICENSE
Classifier: License :: OSI Approved :: MIT License
Classifier: Operating System :: OS Independent
Classifier: Programming Language :: Python :: 3
Requires-Python: <=3.11.7
Requires-Dist: black
Requires-Dist: blosc
Requires-Dist: ezplotly
Requires-Dist: hatch
Requires-Dist: matplotlib
Requires-Dist: natsort
Requires-Dist: nose2
Requires-Dist: numpy
Requires-Dist: opencv-python-headless
